{
  "name": "Mutalist Quanta",
  "image": "InfCrpShockSwarm.png",
  "mastery_level": 2,
  "slot": "Primary",
  "type": "Assault Rifle",
  "trigger": "Auto",
  "noise_level": "45.0m",
  "rate_of_fire": 10,
  "accuracy": 100,
  "clip": 60,
  "max_ammo": 540,
  "reload": 3,
  "projectile_speed": "100.0m/s",
  "disposition": 4,
  "stat_proc": 15,
  "physical_damage": 25,
  "impact_damage": 2.5,
  "puncture_damage": 15,
  "slash_damage": 7.5,
  "crit_chance": 2.5,
  "crit_damage": 1.5,
  "secondary": {
    "elemental_damage_type": "{{Icon|Proc|Radiation|Text}}",
    "elemental_damage": "50.0 (Orb)<br>200.0 (Explosion)"
  },
  "polarities": "{{Icon|Pol|D}}",
  "wiki_link": "/wiki/Mutalist_Quanta",
  "categories": [
    "Infested",
    "Corpus",
    "Primary Weapons",
    "Update 13",
    "Weapons",
    "Research",
    "Radiation Damage Weapons",
    "Assault Rifle",
    "Electricity Damage",
    "Mutalist",
    "Puncture Damage Weapons"
  ]
}
